astrosheild/__init__.py
astrosheild/common_lib/__init__.py
astrosheild/common_lib/hello.py
astrosheild-0.1.dist-info/METADATA
astrosheild-0.1.dist-info/WHEEL
astrosheild-0.1.dist-info/top_level.txt
astrosheild-0.1.dist-info/RECORD
