Metadata-Version: 2.1
Name: astrosheild
Version: 0.1
Summary: A macro package for blackfalcon
Home-page: https://github.com/SpeeDr00t
Author: BlackFlacon
